odoo8_addon_membership_extension-8.0.1.0.1-py2.7-nspkg.pth
odoo_addons/membership_extension/__openerp__.py
odoo_addons/membership_extension/__init__.py
odoo_addons/membership_extension/README.rst
odoo_addons/membership_extension/security/ir.model.access.csv
odoo_addons/membership_extension/models/product_template.py
odoo_addons/membership_extension/models/res_partner.py
odoo_addons/membership_extension/models/product_product.py
odoo_addons/membership_extension/models/account_invoice.py
odoo_addons/membership_extension/models/membership_line.py
odoo_addons/membership_extension/models/membership_category.py
odoo_addons/membership_extension/models/__init__.py
odoo_addons/membership_extension/models/account_invoice_line.py
odoo_addons/membership_extension/i18n/ja.po
odoo_addons/membership_extension/i18n/nl_NL.po
odoo_addons/membership_extension/i18n/lv.po
odoo_addons/membership_extension/i18n/zh_CN.po
odoo_addons/membership_extension/i18n/nb_NO.po
odoo_addons/membership_extension/i18n/uk.po
odoo_addons/membership_extension/i18n/es_AR.po
odoo_addons/membership_extension/i18n/ko.po
odoo_addons/membership_extension/i18n/tr_TR.po
odoo_addons/membership_extension/i18n/ru.po
odoo_addons/membership_extension/i18n/gl_ES.po
odoo_addons/membership_extension/i18n/pt.po
odoo_addons/membership_extension/i18n/fr_CH.po
odoo_addons/membership_extension/i18n/it.po
odoo_addons/membership_extension/i18n/es_CL.po
odoo_addons/membership_extension/i18n/es.po
odoo_addons/membership_extension/i18n/nl_BE.po
odoo_addons/membership_extension/i18n/fr_FR.po
odoo_addons/membership_extension/i18n/ar.po
odoo_addons/membership_extension/i18n/lt.po
odoo_addons/membership_extension/i18n/vi_VN.po
odoo_addons/membership_extension/i18n/ro.po
odoo_addons/membership_extension/i18n/tr.po
odoo_addons/membership_extension/i18n/sr.po
odoo_addons/membership_extension/i18n/es_PY.po
odoo_addons/membership_extension/i18n/mk.po
odoo_addons/membership_extension/i18n/hr.po
odoo8_addon_membership_extension-8.0.1.0.1.dist-info/top_level.txt
odoo8_addon_membership_extension-8.0.1.0.1.dist-info/WHEEL
odoo8_addon_membership_extension-8.0.1.0.1.dist-info/RECORD
odoo8_addon_membership_extension-8.0.1.0.1.dist-info/metadata.json
odoo8_addon_membership_extension-8.0.1.0.1.dist-info/DESCRIPTION.rst
odoo8_addon_membership_extension-8.0.1.0.1.dist-info/METADATA
odoo8_addon_membership_extension-8.0.1.0.1.dist-info/namespace_packages.txt
